{"Event": {"date": "2017-05-09", "publish_timestamp": "1538680515", "published": true, "info": "OSINT - Persirai: New Internet of Things (IoT) Botnet Targets IP Cameras", "threat_level_id": "3", "timestamp": "1538680509", "extends_uuid": "", "uuid": "5bb61071-d0ac-4b8a-8bba-4dc8950d210f", "analysis": "2", "Orgc": {"uuid": "55f6ea5e-2c60-40e5-964f-47a8950d210f", "name": "CIRCL"}, "Tag": [{"colour": "#ffffff", "name": "tlp:white"}, {"colour": "#22681c", "name": "malware_classification:malware-category=\"Botnet\""}, {"colour": "#22681c", "name": "\tmalware_classification:malware-category=\"Botnet\""}, {"colour": "#0088cc", "name": "misp-galaxy:botnet=\"Persirai\""}, {"colour": "#00223b", "name": "osint:source-type=\"blog-post\""}], "Attribute": [{"to_ids": false, "deleted": false, "value": "https://blog.trendmicro.com/trendlabs-security-intelligence/persirai-new-internet-things-iot-botnet-targets-ip-cameras/", "uuid": "5bb610da-7840-4316-b213-4905950d210f", "timestamp": "1538658669", "disable_correlation": false, "comment": "", "category": "External analysis", "type": "link", "Tag": [{"colour": "#00223b", "name": "osint:source-type=\"blog-post\""}]}, {"to_ids": false, "deleted": false, "value": "A new Internet of Things (IoT) botnet called Persirai (Detected by Trend Micro as ELF_PERSIRAI.A) has been discovered targeting over 1,000 Internet Protocol (IP) Camera models based on various Original Equipment Manufacturer (OEM) products. This development comes on the heels of Mirai\u00e2\u20ac\u201dan open-source backdoor malware that caused some of the most notable incidents of 2016 via Distributed Denial-of-Service (DDoS) attacks that compromised IoT devices such as Digital Video Recorders (DVRs) and CCTV cameras\u00e2\u20ac\u201das well as the Hajime botnet.\r\n\r\nWe detected approximately 120,000 IP cameras that are vulnerable to ELF_PERSIRAI.A via Shodan. Many of these vulnerable users are unaware that their IP Cameras are exposed to the internet.", "uuid": "5bb612ca-8a64-47a5-a459-485e950d210f", "timestamp": "1538659027", "disable_correlation": false, "comment": "", "category": "External analysis", "type": "text", "Tag": [{"colour": "#00223b", "name": "osint:source-type=\"blog-post\""}]}, {"to_ids": true, "deleted": false, "value": "load.gtpnet.ir", "uuid": "5bb61739-32dc-44d3-bcf5-4c6d950d210f", "timestamp": "1538660153", "disable_correlation": false, "comment": "C&C server", "category": "Network activity", "type": "hostname"}, {"to_ids": true, "deleted": false, "value": "ntp.gtpnet.ir", "uuid": "5bb6173a-5bc8-4746-a7fd-425f950d210f", "timestamp": "1538660154", "disable_correlation": false, "comment": "C&C server", "category": "Network activity", "type": "hostname"}, {"to_ids": true, "deleted": false, "value": "185.62.189.232", "uuid": "5bb6173f-60ec-47c3-b5da-4bd0950d210f", "timestamp": "1538660159", "disable_correlation": false, "comment": "C&C server", "category": "Network activity", "type": "ip-dst"}, {"to_ids": true, "deleted": false, "value": "95.85.38.103", "uuid": "5bb61740-c0f8-4087-9811-4f8b950d210f", "timestamp": "1538660160", "disable_correlation": false, "comment": "C&C server", "category": "Network activity", "type": "ip-dst"}, {"to_ids": true, "deleted": false, "value": "d00b79a0b47ae38b2d6fbbf994a2075bc70dc88142536f283e8447ed03917e45", "uuid": "5bb61a03-6aa4-4b22-9f78-4283950d210f", "timestamp": "1538660867", "disable_correlation": false, "comment": "Hash detected as ELF_PERSIRAI.A:", "category": "Payload delivery", "type": "sha256"}, {"to_ids": true, "deleted": false, "value": "f974695ae560c6f035e089271ee33a84bebeb940be510ab5066ee958932e310a", "uuid": "5bb61a04-0544-461d-9635-46d1950d210f", "timestamp": "1538660868", "disable_correlation": false, "comment": "Hash detected as ELF_PERSIRAI.A:", "category": "Payload delivery", "type": "sha256"}, {"to_ids": true, "deleted": false, "value": "af4aa29d6e3fce9206b0d21b09b7bc40c3a2128bc5eb02ff239ed2f3549532bb", "uuid": "5bb61a04-a6d4-4105-aae4-43c6950d210f", "timestamp": "1538660868", "disable_correlation": false, "comment": "Hash detected as ELF_PERSIRAI.A:", "category": "Payload delivery", "type": "sha256"}, {"to_ids": true, "deleted": false, "value": "aa443f81cbba72e1692246b5647a9278040400a86afc8e171f54577dc9324f61", "uuid": "5bb61a05-85f4-4a0e-92c5-4370950d210f", "timestamp": "1538660869", "disable_correlation": false, "comment": "Hash detected as ELF_PERSIRAI.A:", "category": "Payload delivery", "type": "sha256"}, {"to_ids": true, "deleted": false, "value": "4a5ff1def77deb11ddecd10f96e4a1de69291f2f879cd83186c6b3fc20bb009a", "uuid": "5bb61a05-8904-4c4f-8a5a-4942950d210f", "timestamp": "1538660869", "disable_correlation": false, "comment": "Hash detected as ELF_PERSIRAI.A:", "category": "Payload delivery", "type": "sha256"}, {"to_ids": true, "deleted": false, "value": "44620a09441305f592fb65d606958611f90e85b62b7ef7149e613d794df3a778", "uuid": "5bb61a09-8e34-41ee-a78d-4e7e950d210f", "timestamp": "1538660873", "disable_correlation": false, "comment": "Hash detected as ELF_PERSIRAI.A:", "category": "Payload delivery", "type": "sha256"}, {"to_ids": true, "deleted": false, "value": "a58769740a750a8b265df65a5b143a06972af2e7d82c5040d908e71474cbaf92", "uuid": "5bb61a0c-14e8-4a85-ba0d-4311950d210f", "timestamp": "1538660876", "disable_correlation": false, "comment": "Hash detected as ELF_PERSIRAI.A:", "category": "Payload delivery", "type": "sha256"}, {"to_ids": true, "deleted": false, "value": "7d7aaa8c9a36324a2c5e9b0a3440344502f28b90776baa6b8dac7ac88a83aef0", "uuid": "5bb61a0d-1720-4ec2-a1f0-4b6a950d210f", "timestamp": "1538660877", "disable_correlation": false, "comment": "Hash detected as ELF_PERSIRAI.A:", "category": "Payload delivery", "type": "sha256"}, {"to_ids": true, "deleted": false, "value": "4a5d00f91a5bb2b6b89ccdabc6c13eab97ede5848275513ded7dfd5803b1074b", "uuid": "5bb61a0d-0208-4bc2-959a-42e2950d210f", "timestamp": "1538660877", "disable_correlation": false, "comment": "Hash detected as ELF_PERSIRAI.A:", "category": "Payload delivery", "type": "sha256"}, {"to_ids": true, "deleted": false, "value": "264e5a7ce9ca7ce7a495ccb02e8f268290fcb1b3e1b05f87d3214b26b0ea9adc", "uuid": "5bb61a0e-500c-4155-825b-452b950d210f", "timestamp": "1538660878", "disable_correlation": false, "comment": "Hash detected as ELF_PERSIRAI.A:", "category": "Payload delivery", "type": "sha256"}, {"to_ids": true, "deleted": false, "value": "ff5db7bdb4de17a77bd4a552f50f0e5488281cedc934fc3707833f90484ef66c", "uuid": "5bb61a0e-dd6c-4fa2-b250-42c4950d210f", "timestamp": "1538660878", "disable_correlation": false, "comment": "Hash detected as ELF_PERSIRAI.A:", "category": "Payload delivery", "type": "sha256"}, {"to_ids": true, "deleted": false, "value": "ec2c39f1dfb75e7b33daceaeda4dbadb8efd9015a9b7e41d595bb28d2cd0180f", "uuid": "5bb61a0f-b75c-4b10-b14b-4d3d950d210f", "timestamp": "1538660879", "disable_correlation": false, "comment": "Hash detected as ELF_PERSIRAI.A:", "category": "Payload delivery", "type": "sha256"}, {"to_ids": true, "deleted": false, "value": "f736948bb4575c10a3175f0078a2b5d36cce1aa4cd635307d03c826e305a7489", "uuid": "5bb61a0f-06f0-4fb1-82eb-4ab6950d210f", "timestamp": "1538660879", "disable_correlation": false, "comment": "Hash detected as ELF_PERSIRAI.A:", "category": "Payload delivery", "type": "sha256"}, {"to_ids": true, "deleted": false, "value": "e0b5c9f874f260c840766eb23c1f69828545d7820f959c8601c41c024044f02c", "uuid": "5bb61a10-ab00-4133-8296-4a96950d210f", "timestamp": "1538660880", "disable_correlation": false, "comment": "Hash detected as ELF_PERSIRAI.A:", "category": "Payload delivery", "type": "sha256"}, {"to_ids": true, "deleted": false, "value": "35317971e346e5b2a8401b2e66b9e62e371ce9532f816cb313216c3647973c32", "uuid": "5bb61a10-469c-473e-ba93-459b950d210f", "timestamp": "1538660880", "disable_correlation": false, "comment": "Hash detected as ELF_PERSIRAI.A:", "category": "Payload delivery", "type": "sha256"}], "Object": [{"template_version": "11", "deleted": false, "template_uuid": "688c46fb-5edb-40a3-8273-1af7923e2215", "meta-category": "file", "comment": "", "sharing_group_id": "0", "distribution": "5", "timestamp": "1538680318", "description": "File object describing a file with meta-information", "uuid": "f309283e-f9b3-4936-9534-ef6866f23c40", "name": "file", "ObjectReference": [{"object_uuid": "f309283e-f9b3-4936-9534-ef6866f23c40", "relationship_type": "analysed-with", "referenced_uuid": "c32be2ac-252d-404e-a391-de2bec4acaf7", "timestamp": "1538680347", "comment": "", "uuid": "5bb6661b-9cdc-4ffe-a798-454602de0b81"}], "Attribute": [{"to_ids": true, "deleted": false, "value": "2f6e964b3f63b13831314c28185bb51a", "object_relation": "md5", "uuid": "24b52a67-d588-4d4f-acc6-531cc4b9e2f3", "timestamp": "1538680315", "disable_correlation": false, "comment": "", "category": "Payload delivery", "type": "md5"}, {"to_ids": true, "deleted": false, "value": "a63417b889491466c912dfbb6d2a34ad27f2bcfe", "object_relation": "sha1", "uuid": "03ef9eff-ea8a-4dba-92ea-ea7658ad001d", "timestamp": "1538680315", "disable_correlation": false, "comment": "", "category": "Payload delivery", "type": "sha1"}, {"to_ids": true, "deleted": false, "value": "7d7aaa8c9a36324a2c5e9b0a3440344502f28b90776baa6b8dac7ac88a83aef0", "object_relation": "sha256", "uuid": "40ff1cf2-3498-4c1a-a0ef-3278217d10c8", "timestamp": "1538680316", "disable_correlation": false, "comment": "", "category": "Payload delivery", "type": "sha256"}]}, {"template_version": "2", "deleted": false, "template_uuid": "d7dd0154-e04f-4c34-a2fb-79f3a3a52aa4", "meta-category": "misc", "comment": "", "sharing_group_id": "0", "distribution": "5", "timestamp": "1538680316", "description": "VirusTotal report", "uuid": "c32be2ac-252d-404e-a391-de2bec4acaf7", "name": "virustotal-report", "Attribute": [{"to_ids": false, "deleted": false, "value": "2018-10-04T00:29:01", "object_relation": "last-submission", "uuid": "7815ca32-703b-430e-a06f-dfb802b2617c", "timestamp": "1538680316", "disable_correlation": false, "comment": "", "category": "Other", "type": "datetime"}, {"to_ids": false, "deleted": false, "value": "https://www.virustotal.com/file/7d7aaa8c9a36324a2c5e9b0a3440344502f28b90776baa6b8dac7ac88a83aef0/analysis/1538612941/", "object_relation": "permalink", "uuid": "b872dfe2-e6a4-46be-93cb-d2d39c54e961", "timestamp": "1538680317", "disable_correlation": false, "comment": "", "category": "External analysis", "type": "link"}, {"to_ids": false, "deleted": false, "value": "27/57", "object_relation": "detection-ratio", "uuid": "b977ae27-2ed8-42ea-af35-31fa7d975feb", "timestamp": "1538680317", "disable_correlation": true, "comment": "", "category": "Other", "type": "text"}]}, {"template_version": "11", "deleted": false, "template_uuid": "688c46fb-5edb-40a3-8273-1af7923e2215", "meta-category": "file", "comment": "", "sharing_group_id": "0", "distribution": "5", "timestamp": "1538680320", "description": "File object describing a file with meta-information", "uuid": "12ef2bb3-f2ac-4266-b693-27631eae3930", "name": "file", "ObjectReference": [{"object_uuid": "12ef2bb3-f2ac-4266-b693-27631eae3930", "relationship_type": "analysed-with", "referenced_uuid": "9d4269eb-edc5-4513-9cdc-fedcf13523d5", "timestamp": "1538680347", "comment": "", "uuid": "5bb6661b-76bc-4361-abf0-432602de0b81"}], "Attribute": [{"to_ids": true, "deleted": false, "value": "428111c22627e1d4ee87705251704422", "object_relation": "md5", "uuid": "33282f75-099d-48b4-ae83-f7c5540f0d88", "timestamp": "1538680317", "disable_correlation": false, "comment": "", "category": "Payload delivery", "type": "md5"}, {"to_ids": true, "deleted": false, "value": "ccc90bd76af9d4b538aa88715027dd062f7c946d", "object_relation": "sha1", "uuid": "cc39a8ec-e498-47b9-9552-7961e7a39a7c", "timestamp": "1538680318", "disable_correlation": false, "comment": "", "category": "Payload delivery", "type": "sha1"}, {"to_ids": true, "deleted": false, "value": "264e5a7ce9ca7ce7a495ccb02e8f268290fcb1b3e1b05f87d3214b26b0ea9adc", "object_relation": "sha256", "uuid": "4e2e9831-6f05-40a8-af03-0eb900d88168", "timestamp": "1538680318", "disable_correlation": false, "comment": "", "category": "Payload delivery", "type": "sha256"}]}, {"template_version": "2", "deleted": false, "template_uuid": "d7dd0154-e04f-4c34-a2fb-79f3a3a52aa4", "meta-category": "misc", "comment": "", "sharing_group_id": "0", "distribution": "5", "timestamp": "1538680319", "description": "VirusTotal report", "uuid": "9d4269eb-edc5-4513-9cdc-fedcf13523d5", "name": "virustotal-report", "Attribute": [{"to_ids": false, "deleted": false, "value": "2018-10-04T00:35:09", "object_relation": "last-submission", "uuid": "836c2dac-1246-4175-a7ac-ad7a3246570e", "timestamp": "1538680319", "disable_correlation": false, "comment": "", "category": "Other", "type": "datetime"}, {"to_ids": false, "deleted": false, "value": "https://www.virustotal.com/file/264e5a7ce9ca7ce7a495ccb02e8f268290fcb1b3e1b05f87d3214b26b0ea9adc/analysis/1538613309/", "object_relation": "permalink", "uuid": "34afc7f8-f731-4458-bea0-0a620d0b2948", "timestamp": "1538680319", "disable_correlation": false, "comment": "", "category": "External analysis", "type": "link"}, {"to_ids": false, "deleted": false, "value": "30/59", "object_relation": "detection-ratio", "uuid": "42f732a2-5783-4fe1-bf28-a299f63a6f65", "timestamp": "1538680320", "disable_correlation": true, "comment": "", "category": "Other", "type": "text"}]}, {"template_version": "11", "deleted": false, "template_uuid": "688c46fb-5edb-40a3-8273-1af7923e2215", "meta-category": "file", "comment": "", "sharing_group_id": "0", "distribution": "5", "timestamp": "1538680323", "description": "File object describing a file with meta-information", "uuid": "f2c1f63f-9a45-43a5-b5f0-aa338180c6a0", "name": "file", "ObjectReference": [{"object_uuid": "f2c1f63f-9a45-43a5-b5f0-aa338180c6a0", "relationship_type": "analysed-with", "referenced_uuid": "f27c2edf-b64f-4038-a3a9-d326a05177bd", "timestamp": "1538680347", "comment": "", "uuid": "5bb6661b-2fa0-4d10-8d8b-461402de0b81"}], "Attribute": [{"to_ids": true, "deleted": false, "value": "9584b6aec418a2af4efac24867a8c7ec", "object_relation": "md5", "uuid": "90e70da4-695a-45d8-beba-5a744c3c8f43", "timestamp": "1538680320", "disable_correlation": false, "comment": "", "category": "Payload delivery", "type": "md5"}, {"to_ids": true, "deleted": false, "value": "22a8faf351768596500dbe6e27c05ad55744da1d", "object_relation": "sha1", "uuid": "e38ba7bd-f315-440f-873d-62d3bf4d8e31", "timestamp": "1538680320", "disable_correlation": false, "comment": "", "category": "Payload delivery", "type": "sha1"}, {"to_ids": true, "deleted": false, "value": "af4aa29d6e3fce9206b0d21b09b7bc40c3a2128bc5eb02ff239ed2f3549532bb", "object_relation": "sha256", "uuid": "2b2cf022-706f-4082-89a4-0482e9989d61", "timestamp": "1538680321", "disable_correlation": false, "comment": "", "category": "Payload delivery", "type": "sha256"}]}, {"template_version": "2", "deleted": false, "template_uuid": "d7dd0154-e04f-4c34-a2fb-79f3a3a52aa4", "meta-category": "misc", "comment": "", "sharing_group_id": "0", "distribution": "5", "timestamp": "1538680321", "description": "VirusTotal report", "uuid": "f27c2edf-b64f-4038-a3a9-d326a05177bd", "name": "virustotal-report", "Attribute": [{"to_ids": false, "deleted": false, "value": "2018-08-28T00:22:07", "object_relation": "last-submission", "uuid": "28299833-823a-4fae-9d26-936806282829", "timestamp": "1538680321", "disable_correlation": false, "comment": "", "category": "Other", "type": "datetime"}, {"to_ids": false, "deleted": false, "value": "https://www.virustotal.com/file/af4aa29d6e3fce9206b0d21b09b7bc40c3a2128bc5eb02ff239ed2f3549532bb/analysis/1535415727/", "object_relation": "permalink", "uuid": "a8b600ec-a940-4775-8d5a-da5e6fb40637", "timestamp": "1538680322", "disable_correlation": false, "comment": "", "category": "External analysis", "type": "link"}, {"to_ids": false, "deleted": false, "value": "31/59", "object_relation": "detection-ratio", "uuid": "6ab72e91-286a-4e59-aed6-7ba109b77661", "timestamp": "1538680322", "disable_correlation": true, "comment": "", "category": "Other", "type": "text"}]}, {"template_version": "11", "deleted": false, "template_uuid": "688c46fb-5edb-40a3-8273-1af7923e2215", "meta-category": "file", "comment": "", "sharing_group_id": "0", "distribution": "5", "timestamp": "1538680325", "description": "File object describing a file with meta-information", "uuid": "9c0321a0-cf1b-4f6b-b67a-69d45877e2d9", "name": "file", "ObjectReference": [{"object_uuid": "9c0321a0-cf1b-4f6b-b67a-69d45877e2d9", "relationship_type": "analysed-with", "referenced_uuid": "1883c73d-680a-4623-9b78-42cfeb491f5b", "timestamp": "1538680347", "comment": "", "uuid": "5bb6661b-fb6c-484f-9d6f-453802de0b81"}], "Attribute": [{"to_ids": true, "deleted": false, "value": "5ebeff1f005804bb8afef91095aac1d9", "object_relation": "md5", "uuid": "2bbd9a12-d0ba-4cdc-9f04-a740655d4fdd", "timestamp": "1538680322", "disable_correlation": false, "comment": "", "category": "Payload delivery", "type": "md5"}, {"to_ids": true, "deleted": false, "value": "c92e07faaad26b4ac98f9cc0c5a24e60dcb25b8a", "object_relation": "sha1", "uuid": "54d8241a-dafa-41f0-a3b5-f9458d39ebc2", "timestamp": "1538680323", "disable_correlation": false, "comment": "", "category": "Payload delivery", "type": "sha1"}, {"to_ids": true, "deleted": false, "value": "4a5d00f91a5bb2b6b89ccdabc6c13eab97ede5848275513ded7dfd5803b1074b", "object_relation": "sha256", "uuid": "b016facb-e211-486f-aa12-dfee52ccc67d", "timestamp": "1538680323", "disable_correlation": false, "comment": "", "category": "Payload delivery", "type": "sha256"}]}, {"template_version": "2", "deleted": false, "template_uuid": "d7dd0154-e04f-4c34-a2fb-79f3a3a52aa4", "meta-category": "misc", "comment": "", "sharing_group_id": "0", "distribution": "5", "timestamp": "1538680324", "description": "VirusTotal report", "uuid": "1883c73d-680a-4623-9b78-42cfeb491f5b", "name": "virustotal-report", "Attribute": [{"to_ids": false, "deleted": false, "value": "2018-10-04T00:40:15", "object_relation": "last-submission", "uuid": "8f277ab7-05c6-46f8-909c-f3381f65afbc", "timestamp": "1538680324", "disable_correlation": false, "comment": "", "category": "Other", "type": "datetime"}, {"to_ids": false, "deleted": false, "value": "https://www.virustotal.com/file/4a5d00f91a5bb2b6b89ccdabc6c13eab97ede5848275513ded7dfd5803b1074b/analysis/1538613615/", "object_relation": "permalink", "uuid": "656ad417-eede-4da8-b924-d1ac777d5cbe", "timestamp": "1538680327", "disable_correlation": false, "comment": "", "category": "External analysis", "type": "link"}, {"to_ids": false, "deleted": false, "value": "30/59", "object_relation": "detection-ratio", "uuid": "6b003f1f-e035-40ad-8331-3e79a4f9ed2e", "timestamp": "1538680328", "disable_correlation": true, "comment": "", "category": "Other", "type": "text"}]}, {"template_version": "11", "deleted": false, "template_uuid": "688c46fb-5edb-40a3-8273-1af7923e2215", "meta-category": "file", "comment": "", "sharing_group_id": "0", "distribution": "5", "timestamp": "1538680331", "description": "File object describing a file with meta-information", "uuid": "36dd4a13-9d43-48b4-b035-a1dd57e1daa8", "name": "file", "ObjectReference": [{"object_uuid": "36dd4a13-9d43-48b4-b035-a1dd57e1daa8", "relationship_type": "analysed-with", "referenced_uuid": "077ee3b9-3db4-4025-957b-3944d40c17d7", "timestamp": "1538680348", "comment": "", "uuid": "5bb6661c-f1c4-4077-8955-4c4b02de0b81"}], "Attribute": [{"to_ids": true, "deleted": false, "value": "f620fb57352e6f393477a65101a4612e", "object_relation": "md5", "uuid": "608de87a-577c-45ba-9efc-633bfba9804e", "timestamp": "1538680328", "disable_correlation": false, "comment": "", "category": "Payload delivery", "type": "md5"}, {"to_ids": true, "deleted": false, "value": "93515d7442d0240272b8d813b300219c53e88dfd", "object_relation": "sha1", "uuid": "2b1110b2-34e6-4efa-ad16-8ddffc43ccdf", "timestamp": "1538680329", "disable_correlation": false, "comment": "", "category": "Payload delivery", "type": "sha1"}, {"to_ids": true, "deleted": false, "value": "a58769740a750a8b265df65a5b143a06972af2e7d82c5040d908e71474cbaf92", "object_relation": "sha256", "uuid": "e8d8bd28-4c6b-4f2f-94a8-91469cc7bff2", "timestamp": "1538680329", "disable_correlation": false, "comment": "", "category": "Payload delivery", "type": "sha256"}]}, {"template_version": "2", "deleted": false, "template_uuid": "d7dd0154-e04f-4c34-a2fb-79f3a3a52aa4", "meta-category": "misc", "comment": "", "sharing_group_id": "0", "distribution": "5", "timestamp": "1538680330", "description": "VirusTotal report", "uuid": "077ee3b9-3db4-4025-957b-3944d40c17d7", "name": "virustotal-report", "Attribute": [{"to_ids": false, "deleted": false, "value": "2018-08-19T23:46:42", "object_relation": "last-submission", "uuid": "3feaaa6c-1944-4d54-b928-151e02b9ba75", "timestamp": "1538680330", "disable_correlation": false, "comment": "", "category": "Other", "type": "datetime"}, {"to_ids": false, "deleted": false, "value": "https://www.virustotal.com/file/a58769740a750a8b265df65a5b143a06972af2e7d82c5040d908e71474cbaf92/analysis/1534722402/", "object_relation": "permalink", "uuid": "4456021c-dde7-45e4-bb39-a42c628b0d31", "timestamp": "1538680333", "disable_correlation": false, "comment": "", "category": "External analysis", "type": "link"}, {"to_ids": false, "deleted": false, "value": "27/58", "object_relation": "detection-ratio", "uuid": "e23bb428-95e6-414a-a60f-e666d298495e", "timestamp": "1538680334", "disable_correlation": true, "comment": "", "category": "Other", "type": "text"}]}, {"template_version": "11", "deleted": false, "template_uuid": "688c46fb-5edb-40a3-8273-1af7923e2215", "meta-category": "file", "comment": "", "sharing_group_id": "0", "distribution": "5", "timestamp": "1538680337", "description": "File object describing a file with meta-information", "uuid": "c0fc4a1e-cd67-415a-b8b9-3b8624427435", "name": "file", "ObjectReference": [{"object_uuid": "c0fc4a1e-cd67-415a-b8b9-3b8624427435", "relationship_type": "analysed-with", "referenced_uuid": "d406e905-e3a5-4d16-b1d2-bc3e6ef6d1fa", "timestamp": "1538680348", "comment": "", "uuid": "5bb6661c-54f8-4679-a815-47b902de0b81"}], "Attribute": [{"to_ids": true, "deleted": false, "value": "912681f6be51afa8c5ab36e691b88e74", "object_relation": "md5", "uuid": "9ff1aa13-17c4-4fea-9fde-e0a7ea8d4705", "timestamp": "1538680334", "disable_correlation": false, "comment": "", "category": "Payload delivery", "type": "md5"}, {"to_ids": true, "deleted": false, "value": "227d1aa69da8250ddbf8898863799e59bdfeb516", "object_relation": "sha1", "uuid": "ded05480-3857-4ced-9d85-0ab4339eb47a", "timestamp": "1538680334", "disable_correlation": false, "comment": "", "category": "Payload delivery", "type": "sha1"}, {"to_ids": true, "deleted": false, "value": "f974695ae560c6f035e089271ee33a84bebeb940be510ab5066ee958932e310a", "object_relation": "sha256", "uuid": "9417d718-1a7e-4b30-ad2a-45d97bf24356", "timestamp": "1538680335", "disable_correlation": false, "comment": "", "category": "Payload delivery", "type": "sha256"}]}, {"template_version": "2", "deleted": false, "template_uuid": "d7dd0154-e04f-4c34-a2fb-79f3a3a52aa4", "meta-category": "misc", "comment": "", "sharing_group_id": "0", "distribution": "5", "timestamp": "1538680335", "description": "VirusTotal report", "uuid": "d406e905-e3a5-4d16-b1d2-bc3e6ef6d1fa", "name": "virustotal-report", "Attribute": [{"to_ids": false, "deleted": false, "value": "2018-08-28T00:21:20", "object_relation": "last-submission", "uuid": "9da3df4d-2a97-4c0f-b9a8-4ee1e3bf41fa", "timestamp": "1538680335", "disable_correlation": false, "comment": "", "category": "Other", "type": "datetime"}, {"to_ids": false, "deleted": false, "value": "https://www.virustotal.com/file/f974695ae560c6f035e089271ee33a84bebeb940be510ab5066ee958932e310a/analysis/1535415680/", "object_relation": "permalink", "uuid": "791bd56a-7de3-419e-9984-b3b8f1126ec6", "timestamp": "1538680336", "disable_correlation": false, "comment": "", "category": "External analysis", "type": "link"}, {"to_ids": false, "deleted": false, "value": "30/59", "object_relation": "detection-ratio", "uuid": "620bf26e-ce72-408a-a9fb-29c061e257be", "timestamp": "1538680336", "disable_correlation": true, "comment": "", "category": "Other", "type": "text"}]}, {"template_version": "11", "deleted": false, "template_uuid": "688c46fb-5edb-40a3-8273-1af7923e2215", "meta-category": "file", "comment": "", "sharing_group_id": "0", "distribution": "5", "timestamp": "1538680339", "description": "File object describing a file with meta-information", "uuid": "7d2c9249-f40e-495c-8f96-64b18ab129e0", "name": "file", "ObjectReference": [{"object_uuid": "7d2c9249-f40e-495c-8f96-64b18ab129e0", "relationship_type": "analysed-with", "referenced_uuid": "41d50336-ea44-4a0b-8e2a-4d5daee47a96", "timestamp": "1538680348", "comment": "", "uuid": "5bb6661c-ced4-4bd5-9664-4d1302de0b81"}], "Attribute": [{"to_ids": true, "deleted": false, "value": "7e1c3834c38984c34b6fd4c741ae3a21", "object_relation": "md5", "uuid": "c926ea2c-261d-4ef5-8257-022da8dd3f46", "timestamp": "1538680336", "disable_correlation": false, "comment": "", "category": "Payload delivery", "type": "md5"}, {"to_ids": true, "deleted": false, "value": "02b850450fcbcdd6b13f03b2121f124543480d62", "object_relation": "sha1", "uuid": "353bad47-ebcb-4db4-815b-f8fdb0be4b50", "timestamp": "1538680337", "disable_correlation": false, "comment": "", "category": "Payload delivery", "type": "sha1"}, {"to_ids": true, "deleted": false, "value": "d00b79a0b47ae38b2d6fbbf994a2075bc70dc88142536f283e8447ed03917e45", "object_relation": "sha256", "uuid": "83d952e9-99fa-45c8-99be-6194f4833034", "timestamp": "1538680337", "disable_correlation": false, "comment": "", "category": "Payload delivery", "type": "sha256"}]}, {"template_version": "2", "deleted": false, "template_uuid": "d7dd0154-e04f-4c34-a2fb-79f3a3a52aa4", "meta-category": "misc", "comment": "", "sharing_group_id": "0", "distribution": "5", "timestamp": "1538680338", "description": "VirusTotal report", "uuid": "41d50336-ea44-4a0b-8e2a-4d5daee47a96", "name": "virustotal-report", "Attribute": [{"to_ids": false, "deleted": false, "value": "2018-10-04T00:51:35", "object_relation": "last-submission", "uuid": "50679951-11f3-4163-bca3-c1a71fc25d9f", "timestamp": "1538680338", "disable_correlation": false, "comment": "", "category": "Other", "type": "datetime"}, {"to_ids": false, "deleted": false, "value": "https://www.virustotal.com/file/d00b79a0b47ae38b2d6fbbf994a2075bc70dc88142536f283e8447ed03917e45/analysis/1538614295/", "object_relation": "permalink", "uuid": "6a957d87-5bf5-4e47-9901-533d3be74a57", "timestamp": "1538680338", "disable_correlation": false, "comment": "", "category": "External analysis", "type": "link"}, {"to_ids": false, "deleted": false, "value": "27/58", "object_relation": "detection-ratio", "uuid": "b95271c3-bd73-4a19-ac07-58509fbe8fc6", "timestamp": "1538680339", "disable_correlation": true, "comment": "", "category": "Other", "type": "text"}]}, {"template_version": "11", "deleted": false, "template_uuid": "688c46fb-5edb-40a3-8273-1af7923e2215", "meta-category": "file", "comment": "", "sharing_group_id": "0", "distribution": "5", "timestamp": "1538680342", "description": "File object describing a file with meta-information", "uuid": "5e99dc31-7b8e-4fc0-b6d2-76c97386fddb", "name": "file", "ObjectReference": [{"object_uuid": "5e99dc31-7b8e-4fc0-b6d2-76c97386fddb", "relationship_type": "analysed-with", "referenced_uuid": "3d0cb0cc-5992-44bd-908d-608dfa518175", "timestamp": "1538680348", "comment": "", "uuid": "5bb6661c-00d0-4b29-aeaa-47f902de0b81"}], "Attribute": [{"to_ids": true, "deleted": false, "value": "b2b129d84723d0ba2f803a546c8b19ae", "object_relation": "md5", "uuid": "40667cb7-b99a-4184-9a36-bdcaf1368400", "timestamp": "1538680339", "disable_correlation": false, "comment": "", "category": "Payload delivery", "type": "md5"}, {"to_ids": true, "deleted": false, "value": "7a0485e52aa09f63d41e471fd736584c06c3dab6", "object_relation": "sha1", "uuid": "de0721c4-14d6-4c3c-8b0c-74a414f55360", "timestamp": "1538680339", "disable_correlation": false, "comment": "", "category": "Payload delivery", "type": "sha1"}, {"to_ids": true, "deleted": false, "value": "44620a09441305f592fb65d606958611f90e85b62b7ef7149e613d794df3a778", "object_relation": "sha256", "uuid": "6f071f79-d240-4035-953b-3170c06b89c1", "timestamp": "1538680340", "disable_correlation": false, "comment": "", "category": "Payload delivery", "type": "sha256"}]}, {"template_version": "2", "deleted": false, "template_uuid": "d7dd0154-e04f-4c34-a2fb-79f3a3a52aa4", "meta-category": "misc", "comment": "", "sharing_group_id": "0", "distribution": "5", "timestamp": "1538680340", "description": "VirusTotal report", "uuid": "3d0cb0cc-5992-44bd-908d-608dfa518175", "name": "virustotal-report", "Attribute": [{"to_ids": false, "deleted": false, "value": "2018-09-18T19:47:01", "object_relation": "last-submission", "uuid": "a6d21e1e-4762-45a8-8397-1e40b79d6f0a", "timestamp": "1538680340", "disable_correlation": false, "comment": "", "category": "Other", "type": "datetime"}, {"to_ids": false, "deleted": false, "value": "https://www.virustotal.com/file/44620a09441305f592fb65d606958611f90e85b62b7ef7149e613d794df3a778/analysis/1537300021/", "object_relation": "permalink", "uuid": "25405b32-6b81-42dc-a247-ebc03f770730", "timestamp": "1538680341", "disable_correlation": false, "comment": "", "category": "External analysis", "type": "link"}, {"to_ids": false, "deleted": false, "value": "28/58", "object_relation": "detection-ratio", "uuid": "85bba342-833d-452d-ae52-93ca69be210c", "timestamp": "1538680341", "disable_correlation": true, "comment": "", "category": "Other", "type": "text"}]}, {"template_version": "11", "deleted": false, "template_uuid": "688c46fb-5edb-40a3-8273-1af7923e2215", "meta-category": "file", "comment": "", "sharing_group_id": "0", "distribution": "5", "timestamp": "1538680344", "description": "File object describing a file with meta-information", "uuid": "ed841816-818e-4245-b6dd-f2309f700681", "name": "file", "ObjectReference": [{"object_uuid": "ed841816-818e-4245-b6dd-f2309f700681", "relationship_type": "analysed-with", "referenced_uuid": "249cc05d-c4f2-49e8-a6a1-7fb0437d810d", "timestamp": "1538680348", "comment": "", "uuid": "5bb6661c-e168-41ba-9dad-49e902de0b81"}], "Attribute": [{"to_ids": true, "deleted": false, "value": "cfb80e0b1e3927ebc1069b8fdc468072", "object_relation": "md5", "uuid": "06167403-7850-4f72-beef-9c58f7efa820", "timestamp": "1538680341", "disable_correlation": false, "comment": "", "category": "Payload delivery", "type": "md5"}, {"to_ids": true, "deleted": false, "value": "64bd5ba88d7e7104dc1a5586171e83825815362d", "object_relation": "sha1", "uuid": "04f39242-2c21-4b18-af64-c5e8a21b9635", "timestamp": "1538680342", "disable_correlation": false, "comment": "", "category": "Payload delivery", "type": "sha1"}, {"to_ids": true, "deleted": false, "value": "4a5ff1def77deb11ddecd10f96e4a1de69291f2f879cd83186c6b3fc20bb009a", "object_relation": "sha256", "uuid": "20c1c44e-003c-4093-b594-6ded9eeca681", "timestamp": "1538680342", "disable_correlation": false, "comment": "", "category": "Payload delivery", "type": "sha256"}]}, {"template_version": "2", "deleted": false, "template_uuid": "d7dd0154-e04f-4c34-a2fb-79f3a3a52aa4", "meta-category": "misc", "comment": "", "sharing_group_id": "0", "distribution": "5", "timestamp": "1538680344", "description": "VirusTotal report", "uuid": "249cc05d-c4f2-49e8-a6a1-7fb0437d810d", "name": "virustotal-report", "Attribute": [{"to_ids": false, "deleted": false, "value": "2018-10-01T16:00:37", "object_relation": "last-submission", "uuid": "960ff2ae-bf7a-49c3-ab42-4134855d21d9", "timestamp": "1538680344", "disable_correlation": false, "comment": "", "category": "Other", "type": "datetime"}, {"to_ids": false, "deleted": false, "value": "https://www.virustotal.com/file/4a5ff1def77deb11ddecd10f96e4a1de69291f2f879cd83186c6b3fc20bb009a/analysis/1538409637/", "object_relation": "permalink", "uuid": "146485a6-71f5-41d8-800b-4ac4f679f33b", "timestamp": "1538680344", "disable_correlation": false, "comment": "", "category": "External analysis", "type": "link"}, {"to_ids": false, "deleted": false, "value": "30/58", "object_relation": "detection-ratio", "uuid": "b5bc8306-34a2-4eb6-9dd5-893115f7c124", "timestamp": "1538680345", "disable_correlation": true, "comment": "", "category": "Other", "type": "text"}]}, {"template_version": "11", "deleted": false, "template_uuid": "688c46fb-5edb-40a3-8273-1af7923e2215", "meta-category": "file", "comment": "", "sharing_group_id": "0", "distribution": "5", "timestamp": "1538680348", "description": "File object describing a file with meta-information", "uuid": "e379a5ec-5b7a-48c0-ad91-c00272e066c8", "name": "file", "ObjectReference": [{"object_uuid": "e379a5ec-5b7a-48c0-ad91-c00272e066c8", "relationship_type": "analysed-with", "referenced_uuid": "bf3cb4e2-3ce7-4abb-b77a-91e1fa59320b", "timestamp": "1538680348", "comment": "", "uuid": "5bb6661c-4778-45ae-a8a3-460102de0b81"}], "Attribute": [{"to_ids": true, "deleted": false, "value": "10d899e46e0df86ba6e6a4754de331d9", "object_relation": "md5", "uuid": "68d4af39-d36f-4203-adca-0e8aaf59a19e", "timestamp": "1538680345", "disable_correlation": false, "comment": "", "category": "Payload delivery", "type": "md5"}, {"to_ids": true, "deleted": false, "value": "29aabf21557507699503251e8e19ff77ee61f1bc", "object_relation": "sha1", "uuid": "5ac792b2-96eb-41ce-a68b-57c2f740e5b5", "timestamp": "1538680345", "disable_correlation": false, "comment": "", "category": "Payload delivery", "type": "sha1"}, {"to_ids": true, "deleted": false, "value": "aa443f81cbba72e1692246b5647a9278040400a86afc8e171f54577dc9324f61", "object_relation": "sha256", "uuid": "2c2142c5-23e4-42b8-92e1-7427af655547", "timestamp": "1538680346", "disable_correlation": false, "comment": "", "category": "Payload delivery", "type": "sha256"}]}, {"template_version": "2", "deleted": false, "template_uuid": "d7dd0154-e04f-4c34-a2fb-79f3a3a52aa4", "meta-category": "misc", "comment": "", "sharing_group_id": "0", "distribution": "5", "timestamp": "1538680346", "description": "VirusTotal report", "uuid": "bf3cb4e2-3ce7-4abb-b77a-91e1fa59320b", "name": "virustotal-report", "Attribute": [{"to_ids": false, "deleted": false, "value": "2018-10-04T00:21:25", "object_relation": "last-submission", "uuid": "0911b7f8-578a-470b-a17b-1d302ea16696", "timestamp": "1538680346", "disable_correlation": false, "comment": "", "category": "Other", "type": "datetime"}, {"to_ids": false, "deleted": false, "value": "https://www.virustotal.com/file/aa443f81cbba72e1692246b5647a9278040400a86afc8e171f54577dc9324f61/analysis/1538612485/", "object_relation": "permalink", "uuid": "b3cc844b-5bf3-4cb8-b122-eee753b95a86", "timestamp": "1538680347", "disable_correlation": false, "comment": "", "category": "External analysis", "type": "link"}, {"to_ids": false, "deleted": false, "value": "28/58", "object_relation": "detection-ratio", "uuid": "dd676758-854f-4bee-b4b2-4942e2c6efc7", "timestamp": "1538680347", "disable_correlation": true, "comment": "", "category": "Other", "type": "text"}]}]}}