{"Event": {"info": "OSINT - CCleanup: A Vast Number of Machines at Risk", "Tag": [{"colour": "#ffffff", "exportable": true, "name": "tlp:white"}], "publish_timestamp": "1505723528", "timestamp": "1505962473", "analysis": "2", "Attribute": [{"comment": "", "category": "External analysis", "uuid": "59bf81ab-1a68-4034-b35b-b063950d210f", "timestamp": "1505723360", "to_ids": false, "value": "Supply chain attacks are a very effective way to distribute malicious software into target organizations. This is because with supply chain attacks, the attackers are relying on the trust relationship between a manufacturer or supplier and a customer. This trust relationship is then abused to attack organizations and individuals and may be performed for a number of different reasons. The Nyetya worm that was released into the wild earlier in 2017 showed just how potent these types of attacks can be. Frequently, as with Nyetya, the initial infection vector can remain elusive for quite some time. Luckily with tools like AMP the additional visibility can usually help direct attention to the initial vector. \r\n\r\nTalos recently observed a case where the download servers used by software vendor to distribute a legitimate software package were leveraged to deliver malware to unsuspecting victims. For a period of time, the legitimate signed version of CCleaner 5.33 being distributed by Avast also contained a multi-stage malware payload that rode on top of the installation of CCleaner. CCleaner boasted over 2 billion total downloads by November of 2016 with a growth rate of 5 million additional users per week. Given the potential damage that could be caused by a network of infected computers even a tiny fraction of this size we decided to move quickly. On September 13, 2017 Cisco Talos immediately notified Avast of our findings so that they could initiate appropriate response activities. The following sections will discuss the specific details regarding this attack.", "Tag": [{"colour": "#00223b", "exportable": true, "name": "osint:source-type=\"blog-post\""}], "disable_correlation": false, "object_relation": null, "type": "text"}, {"comment": "", "category": "External analysis", "uuid": "59bf81de-a514-4989-8f8b-ade3950d210f", "timestamp": "1505723360", "to_ids": false, "value": "http://blog.talosintelligence.com/2017/09/avast-distributes-malware.html", "Tag": [{"colour": "#00223b", "exportable": true, "name": "osint:source-type=\"blog-post\""}], "disable_correlation": false, "object_relation": null, "type": "link"}, {"comment": "DGA Domain", "category": "Network activity", "uuid": "59bf830e-cec0-41ad-9c89-ade8950d210f", "timestamp": "1505723360", "to_ids": true, "value": "ab6d54340c1a.com", "disable_correlation": false, "object_relation": null, "type": "domain"}, {"comment": "DGA Domain", "category": "Network activity", "uuid": "59bf830e-2ab0-4d84-896f-ade8950d210f", "timestamp": "1505723360", "to_ids": true, "value": "aba9a949bc1d.com", "disable_correlation": false, "object_relation": null, "type": "domain"}, {"comment": "DGA Domain", "category": "Network activity", "uuid": "59bf830e-c370-4a85-ac14-ade8950d210f", "timestamp": "1505723360", "to_ids": true, "value": "ab2da3d400c20.com", "disable_correlation": false, "object_relation": null, "type": "domain"}, {"comment": "DGA Domain", "category": "Network activity", "uuid": "59bf830e-842c-46ac-8d67-ade8950d210f", "timestamp": "1505723360", "to_ids": true, "value": "ab3520430c23.com", "disable_correlation": false, "object_relation": null, "type": "domain"}, {"comment": "DGA Domain", "category": "Network activity", "uuid": "59bf830e-a268-44fa-9f3e-ade8950d210f", "timestamp": "1505723360", "to_ids": true, "value": "ab1c403220c27.com", "disable_correlation": false, "object_relation": null, "type": "domain"}, {"comment": "DGA Domain", "category": "Network activity", "uuid": "59bf830e-c93c-4bb2-acb8-ade8950d210f", "timestamp": "1505723360", "to_ids": true, "value": "ab1abad1d0c2a.com", "disable_correlation": false, "object_relation": null, "type": "domain"}, {"comment": "DGA Domain", "category": "Network activity", "uuid": "59bf830e-2594-4ffc-a14c-ade8950d210f", "timestamp": "1505723360", "to_ids": true, "value": "ab8cee60c2d.com", "disable_correlation": false, "object_relation": null, "type": "domain"}, {"comment": "DGA Domain", "category": "Network activity", "uuid": "59bf830e-6c70-405f-84bd-ade8950d210f", "timestamp": "1505723360", "to_ids": true, "value": "ab1145b758c30.com", "disable_correlation": false, "object_relation": null, "type": "domain"}, {"comment": "DGA Domain", "category": "Network activity", "uuid": "59bf830e-a8c0-4da4-a47e-ade8950d210f", "timestamp": "1505723360", "to_ids": true, "value": "ab890e964c34.com", "disable_correlation": false, "object_relation": null, "type": "domain"}, {"comment": "DGA Domain", "category": "Network activity", "uuid": "59bf830e-795c-4960-b8e6-ade8950d210f", "timestamp": "1505723360", "to_ids": true, "value": "ab3d685a0c37.com", "disable_correlation": false, "object_relation": null, "type": "domain"}, {"comment": "DGA Domain", "category": "Network activity", "uuid": "59bf830e-5a3c-4520-90b5-ade8950d210f", "timestamp": "1505723360", "to_ids": true, "value": "ab70a139cc3a.com", "disable_correlation": false, "object_relation": null, "type": "domain"}, {"comment": "", "category": "Payload delivery", "uuid": "59bf8363-93b8-4e18-99c4-91da950d210f", "timestamp": "1505723360", "to_ids": true, "value": "6f7840c77f99049d788155c1351e1560b62b8ad18ad0e9adda8218b9f432f0a9", "disable_correlation": false, "object_relation": null, "type": "sha256"}, {"comment": "", "category": "Payload delivery", "uuid": "59bf8363-5410-4f41-8314-91da950d210f", "timestamp": "1505723360", "to_ids": true, "value": "1a4a5123d7b2c534cb3e3168f7032cf9ebf38b9a2a97226d0fdb7933cf6030ff", "disable_correlation": false, "object_relation": null, "type": "sha256"}, {"comment": "", "category": "Payload delivery", "uuid": "59bf8363-3ab4-4a1d-8a29-91da950d210f", "timestamp": "1505723360", "to_ids": true, "value": "36b36ee9515e0a60629d2c722b006b33e543dce1c8c2611053e0651a0bfdb2e9", "disable_correlation": false, "object_relation": null, "type": "sha256"}, {"comment": "", "category": "Network activity", "uuid": "59bf8370-9638-404c-a472-91d1950d210f", "timestamp": "1505723360", "to_ids": true, "value": "216.126.225.148", "disable_correlation": false, "object_relation": null, "type": "ip-dst"}, {"comment": "", "category": "Artifacts dropped", "uuid": "59bf83c5-7b64-4222-a750-9958950d210f", "timestamp": "1505723360", "to_ids": true, "value": "S:\\workspace\\ccleaner\\branches\\v5.33\\bin\\CCleaner\\Release\\CCleaner.pdb", "disable_correlation": false, "object_relation": null, "type": "pdb"}, {"comment": "- Xchecked via VT: 36b36ee9515e0a60629d2c722b006b33e543dce1c8c2611053e0651a0bfdb2e9", "category": "Payload delivery", "uuid": "59bf83e1-bca0-4960-95c0-aa4b02de0b81", "timestamp": "1505723361", "to_ids": true, "value": "7e9cfa3cca5000fe56e4cf5c660f7939487e531a", "disable_correlation": false, "object_relation": null, "type": "sha1"}, {"comment": "- Xchecked via VT: 36b36ee9515e0a60629d2c722b006b33e543dce1c8c2611053e0651a0bfdb2e9", "category": "Payload delivery", "uuid": "59bf83e1-e588-4e74-bbb8-aa4b02de0b81", "timestamp": "1505723361", "to_ids": true, "value": "d488e4b61c233293bec2ee09553d3a2f", "disable_correlation": false, "object_relation": null, "type": "md5"}, {"comment": "- Xchecked via VT: 36b36ee9515e0a60629d2c722b006b33e543dce1c8c2611053e0651a0bfdb2e9", "category": "External analysis", "uuid": "59bf83e1-fbdc-4959-bb43-aa4b02de0b81", "timestamp": "1505723361", "to_ids": false, "value": "https://www.virustotal.com/file/36b36ee9515e0a60629d2c722b006b33e543dce1c8c2611053e0651a0bfdb2e9/analysis/1505722714/", "disable_correlation": false, "object_relation": null, "type": "link"}, {"comment": "- Xchecked via VT: 1a4a5123d7b2c534cb3e3168f7032cf9ebf38b9a2a97226d0fdb7933cf6030ff", "category": "Payload delivery", "uuid": "59bf83e1-02ac-466e-b8b5-aa4b02de0b81", "timestamp": "1505723361", "to_ids": true, "value": "c705c0b0210ebda6a3301c6ca9c6091b2ee11d5b", "disable_correlation": false, "object_relation": null, "type": "sha1"}, {"comment": "- Xchecked via VT: 1a4a5123d7b2c534cb3e3168f7032cf9ebf38b9a2a97226d0fdb7933cf6030ff", "category": "Payload delivery", "uuid": "59bf83e1-8704-45b8-b901-aa4b02de0b81", "timestamp": "1505723361", "to_ids": true, "value": "75735db7291a19329190757437bdb847", "disable_correlation": false, "object_relation": null, "type": "md5"}, {"comment": "- Xchecked via VT: 1a4a5123d7b2c534cb3e3168f7032cf9ebf38b9a2a97226d0fdb7933cf6030ff", "category": "External analysis", "uuid": "59bf83e1-1814-4c13-9596-aa4b02de0b81", "timestamp": "1505723361", "to_ids": false, "value": "https://www.virustotal.com/file/1a4a5123d7b2c534cb3e3168f7032cf9ebf38b9a2a97226d0fdb7933cf6030ff/analysis/1505723218/", "disable_correlation": false, "object_relation": null, "type": "link"}, {"comment": "- Xchecked via VT: 6f7840c77f99049d788155c1351e1560b62b8ad18ad0e9adda8218b9f432f0a9", "category": "Payload delivery", "uuid": "59bf83e1-f5b4-41d8-a784-aa4b02de0b81", "timestamp": "1505723361", "to_ids": true, "value": "8983a49172af96178458266f93d65fa193eaaef2", "disable_correlation": false, "object_relation": null, "type": "sha1"}, {"comment": "- Xchecked via VT: 6f7840c77f99049d788155c1351e1560b62b8ad18ad0e9adda8218b9f432f0a9", "category": "Payload delivery", "uuid": "59bf83e1-0e98-412b-9ecc-aa4b02de0b81", "timestamp": "1505723361", "to_ids": true, "value": "ef694b89ad7addb9a16bb6f26f1efaf7", "disable_correlation": false, "object_relation": null, "type": "md5"}, {"comment": "- Xchecked via VT: 6f7840c77f99049d788155c1351e1560b62b8ad18ad0e9adda8218b9f432f0a9", "category": "External analysis", "uuid": "59bf83e1-68f0-4473-8a28-aa4b02de0b81", "timestamp": "1505723361", "to_ids": false, "value": "https://www.virustotal.com/file/6f7840c77f99049d788155c1351e1560b62b8ad18ad0e9adda8218b9f432f0a9/analysis/1505722818/", "disable_correlation": false, "object_relation": null, "type": "link"}, {"comment": "", "category": "Artifacts dropped", "uuid": "59bf846d-9af0-4582-ab2c-aa4b950d210f", "timestamp": "1505723501", "to_ids": true, "value": "HKLM\\SOFTWARE\\Piriform\\Agomo", "disable_correlation": false, "object_relation": null, "type": "regkey"}], "extends_uuid": "", "published": false, "date": "2017-09-18", "Orgc": {"uuid": "55f6ea5e-2c60-40e5-964f-47a8950d210f", "name": "CIRCL"}, "threat_level_id": "3", "uuid": "59bf8143-8b5c-4146-b820-91d9950d210f"}}