{"Event": {"timestamp": "1570891290", "threat_level_id": "2", "published": true, "date": "2019-10-10", "uuid": "5da1e411-c430-4fd6-bb05-9c81c0a8ab16", "publish_timestamp": "1570891295", "analysis": "2", "info": "Mahalo FIN7: Responding to the Criminal Operators\u00e2\u20ac\u2122 New Tools and Techniques", "Orgc": {"uuid": "56c42374-fdb8-4544-a218-41ffc0a8ab16", "name": "CUDESO"}, "Tag": [{"colour": "#0088cc", "exportable": true, "name": "misp-galaxy:mitre-enterprise-attack-attack-pattern=\"Data Encrypted - T1022\""}, {"colour": "#0088cc", "exportable": true, "name": "misp-galaxy:mitre-enterprise-attack-attack-pattern=\"Obfuscated Files or Information - T1027\""}, {"colour": "#0088cc", "exportable": true, "name": "misp-galaxy:mitre-enterprise-attack-attack-pattern=\"DLL Search Order Hijacking - T1038\""}, {"colour": "#0088cc", "exportable": true, "name": "misp-galaxy:mitre-enterprise-attack-attack-pattern=\"Code Signing - T1116\""}, {"colour": "#0088cc", "exportable": true, "name": "misp-galaxy:mitre-enterprise-attack-attack-pattern=\"Execution through Module Load - T1129\""}, {"colour": "#0088cc", "exportable": true, "name": "misp-galaxy:mitre-enterprise-attack-attack-pattern=\"Deobfuscate/Decode Files or Information - T1140\""}, {"colour": "#0088cc", "exportable": true, "name": "misp-galaxy:mitre-enterprise-attack-attack-pattern=\"Execution through API - T1106\""}, {"colour": "#0088cc", "exportable": true, "name": "misp-galaxy:mitre-enterprise-attack-attack-pattern=\"File Deletion - T1107\""}, {"colour": "#0088cc", "exportable": true, "name": "misp-galaxy:mitre-enterprise-attack-attack-pattern=\"Hooking - T1179\""}, {"colour": "#00d622", "exportable": true, "name": "tlp:white"}], "Attribute": [{"timestamp": "1570891028", "comment": "Boostwrite (signed)", "category": "Payload delivery", "value": "a67d6e87283c34459b4660f19747a306", "type": "md5", "uuid": "5da1e514-5330-4c2f-94c0-9c80c0a8ab16", "to_ids": true, "object_relation": null}, {"timestamp": "1570891028", "comment": "Boostwrite (signed)", "category": "Payload delivery", "value": "a873f3417d54220e978d0ca9ceb63cf13ec71f84", "type": "sha1", "uuid": "5da1e514-7890-4b23-b756-9c80c0a8ab16", "to_ids": true, "object_relation": null}, {"timestamp": "1570891028", "comment": "Boostwrite (signed)", "category": "Payload delivery", "value": "18cc54e2fbdad5a317b6aeb2e7db3973cc5ffb01bbf810869d79e9cb3bf02bd5", "type": "sha256", "uuid": "5da1e514-aa14-4cdb-9837-9c80c0a8ab16", "to_ids": true, "object_relation": null}, {"timestamp": "1570891028", "comment": "C2", "category": "Network activity", "value": "109.230.199.227", "type": "ip-dst", "uuid": "5da1e514-d154-4eef-82f0-9c80c0a8ab16", "to_ids": true, "object_relation": null}, {"timestamp": "1570891028", "comment": "Boostwrite (unsigned)", "category": "Payload delivery", "value": "af2f4142463f42548b8650a3adf5ceb2", "type": "md5", "uuid": "5da1e514-736c-4f93-b694-9c80c0a8ab16", "to_ids": true, "object_relation": null}, {"timestamp": "1570891028", "comment": "Boostwrite (unsigned)", "category": "Payload delivery", "value": "09f3c9ae382fbd29fb47ecdfeb3bb149d7e961a1", "type": "sha1", "uuid": "5da1e514-fb28-4e09-8867-9c80c0a8ab16", "to_ids": true, "object_relation": null}, {"timestamp": "1570891028", "comment": "Boostwrite (unsigned)", "category": "Payload delivery", "value": "8773aeb53d9034dc8de339651e61d8d6ae0a895c4c89b670d501db8dc60cd2d0", "type": "sha256", "uuid": "5da1e514-7ed8-4408-a666-9c80c0a8ab16", "to_ids": true, "object_relation": null}, {"timestamp": "1570891028", "comment": "C2", "category": "Payload delivery", "value": "F:\\projects\\DWriteImpl\\Release\\DWriteImpl.pdb", "type": "filename", "uuid": "5da1e514-1a70-478e-bf30-9c80c0a8ab16", "to_ids": true, "object_relation": null}, {"timestamp": "1570891290", "comment": "", "category": "External analysis", "value": "https://www.fireeye.com/blog/threat-research/2019/10/mahalo-fin7-responding-to-new-tools-and-techniques.html", "type": "link", "uuid": "5da1e61a-75b0-41dd-a99b-9c7fc0a8ab16", "to_ids": false, "object_relation": null}]}}